README.md
setup.cfg
setup.py
cryocon/__init__.py
cryocon/cryocon.py
cryocon/simulator.py
cryocon.egg-info/PKG-INFO
cryocon.egg-info/SOURCES.txt
cryocon.egg-info/dependency_links.txt
cryocon.egg-info/entry_points.txt
cryocon.egg-info/requires.txt
cryocon.egg-info/top_level.txt
cryocon/tango/__init__.py
cryocon/tango/server/__init__.py
cryocon/tango/server/cryocon.py