Metadata-Version: 2.1
Name: cryocon
Version: 3.1.9
Summary: CryCon library
Home-page: https://github.com/ALBA-Synchrotron/cryocon
Author: Jairo Moldes
Author-email: jmoldes@cells.es
License: LGPLv3
Keywords: cryocon,library,tango,simulator
Platform: UNKNOWN
Classifier: Development Status :: 2 - Pre-Alpha
Classifier: Intended Audience :: Developers
Classifier: Natural Language :: English
Classifier: Programming Language :: Python :: 3
Classifier: Programming Language :: Python :: 3.5
Classifier: Programming Language :: Python :: 3.6
Classifier: Programming Language :: Python :: 3.7
Classifier: Programming Language :: Python :: 3.8
Requires-Python: >=3.5
Provides-Extra: tango
Provides-Extra: simulator
Provides-Extra: all
